{
	"black":        "#485867",
	"dark_blue":    "#868cb3",
	"dark_green":   "#87b386",
	"dark_cyan":    "#86b3b3",
	"dark_red":     "#b38686",
	"dark_magenta": "#b386b2",
	"dark_yellow":  "#aab386",
	"gray":         "#E3EFEF",
	"dark_gray":    "#5A6D7A",
	"blue":         "#98AFB5",
	"green":        "#6D828E",
	"cyan":         "#B0C5C8",
	"red":          "#d8bba2",
	"magenta":      "#b39f9f",
	"yellow":       "#8299A1",
	"white":        "#C9DBDC",

    "screen_colors": "white,black",
	"popup_colors":  "dark_magenta,gray",

	"font_face":      "Consolas",
	"font_true_type": true,
	"font_size":      "8x20",
	"font_weight":    700,

	"cursor_size": "large",

	"window_size":        "85x26",
	"screen_buffer_size": "80x200",

	"command_history_length": 50,
	"num_history_buffers":     4,

	"quick_edit":  false,
	"insert_mode": true,
	"fullscreen":  false,

	"load_console_IME":  true
}
