{
	"black":        "#ffffff",
	"dark_blue":    "#8250df",
	"dark_green":   "#0a3069",
	"dark_cyan":    "#0550ae",
	"dark_red":     "#8a4600",
	"dark_magenta": "#b35900",
	"dark_yellow":  "#bf8700",
	"gray":         "#424a53",
	"dark_gray":    "#f6f8fa",
	"blue":         "#8250df",
	"green":        "#0a3069",
	"cyan":         "#0550ae",
	"red":          "#8a4600",
	"magenta":      "#b35900",
	"yellow":       "#bf8700",
	"white":        "#24292f",
	"screen_colors": "gray,black",
	"popup_colors":  "dark_magenta,white"
}
