{
	"black":        "#222436",
	"dark_blue":    "#82aaff",
	"dark_green":   "#c3e88d",
	"dark_cyan":    "#86e1fc",
	"dark_red":     "#ff757f",
	"dark_magenta": "#fca7ea",
	"dark_yellow":  "#ffc777",
	"gray":         "#3b4261",
	"dark_gray":    "#1e2030",
	"blue":         "#82aaff",
	"green":        "#c3e88d",
	"cyan":         "#86e1fc",
	"red":          "#ff757f",
	"magenta":      "#fca7ea",
	"yellow":       "#ffc777",
	"white":        "#c8d3f5",
	"screen_colors": "gray,black",
	"popup_colors":  "dark_magenta,white"
}
