{
	"black":        "#151515",
	"dark_blue":    "#6A9FB5",
	"dark_green":   "#90A959",
	"dark_cyan":    "#75B5AA",
	"dark_red":     "#AC4142",
	"dark_magenta": "#AA759F",
	"dark_yellow":  "#F4BF75",
	"gray":         "#F5F5F5",
	"dark_gray":    "#202020",
	"blue":         "#B0B0B0",
	"green":        "#303030",
	"cyan":         "#D0D0D0",
	"red":          "#D28445",
	"magenta":      "#8F5536",
	"yellow":       "#505050",
	"white":        "#E0E0E0",
	"screen_colors": "white,black",
	"popup_colors":  "dark_magenta,gray"
}
