{
	"black":        "#2d302f",
	"dark_blue":    "#b0a4e3",
	"dark_green":   "#8ab361",
	"dark_cyan":    "#30dff3",
	"dark_red":     "#f9906f",
	"dark_magenta": "#cca4e3",
	"dark_yellow":  "#f0c239",
	"gray":         "#fcfefd",
	"dark_gray":    "#434846",
	"blue":         "#cad8d2",
	"green":        "#5a605d",
	"cyan":         "#e0f0ef",
	"red":          "#b38a61",
	"magenta":      "#ca6924",
	"yellow":       "#9da8a3",
	"white":        "#ecf6f2",
	"screen_colors": "white,black",
	"popup_colors":  "dark_magenta,gray"
}
