{
	"black":        "#000000",
	"dark_blue":    "#96cbfe",
	"dark_green":   "#a8ff60",
	"dark_cyan":    "#c6c5fe",
	"dark_red":     "#ff6c60",
	"dark_magenta": "#ff73fd",
	"dark_yellow":  "#ffffb6",
	"gray":         "#fdfbee",
	"dark_gray":    "#242422",
	"blue":         "#918f88",
	"green":        "#484844",
	"cyan":         "#b5b3aa",
	"red":          "#e9c062",
	"magenta":      "#b18a3d",
	"yellow":       "#6c6c66",
	"white":        "#d9d7cc",

	"screen_colors": "white,black",
	"popup_colors":  "dark_magenta,gray",

	"font_face":      "Consolas",
	"font_true_type": true,
	"font_size":      "0x20",
	"font_weight":    700,

	"cursor_size": "large",

	"window_size":        "85x26",
	"screen_buffer_size": "80x200",

	"command_history_length": 50,
	"num_history_buffers":     4,

	"quick_edit":  false,
	"insert_mode": true,
	"fullscreen":  false,

	"load_console_IME":  true
}
