{
	"black":        "#1e1e1e",
	"dark_blue":    "#7587a6",
	"dark_green":   "#8f9d6a",
	"dark_cyan":    "#afc4db",
	"dark_red":     "#cf6a4c",
	"dark_magenta": "#9b859d",
	"dark_yellow":  "#f9ee98",
	"gray":         "#a7a7a7",
	"dark_gray":    "#323537",
	"blue":         "#7587a6",
	"green":        "#8f9d6a",
	"cyan":         "#afc4db",
	"red":          "#cf6a4c",
	"magenta":      "#9b859d",
	"yellow":       "#f9ee98",
	"white":        "#ffffff",
	"screen_colors": "gray,black",
	"popup_colors":  "dark_magenta,white"
}
