{
	"black":        "#232323",
	"dark_blue":    "#376388",
	"dark_green":   "#71983b",
	"dark_cyan":    "#c57d42",
	"dark_red":     "#cc5450",
	"dark_magenta": "#d7ab54",
	"dark_yellow":  "#307878",
	"gray":         "#dbdbdb",
	"dark_gray":    "#1c1c1c",
	"blue":         "#376388",
	"green":        "#71983b",
	"cyan":         "#c57d42",
	"red":          "#cc5450",
	"magenta":      "#d7ab54",
	"yellow":       "#307878",
	"white":        "#1c1c1c",
	"screen_colors": "gray,black",
	"popup_colors":  "dark_magenta,white"
}
