{
	"black":        "#212121",
	"dark_blue":    "#82AAFF",
	"dark_green":   "#C3E88D",
	"dark_cyan":    "#89DDFF",
	"dark_red":     "#F07178",
	"dark_magenta": "#C792EA",
	"dark_yellow":  "#FFCB6B",
	"gray":         "#FFFFFF",
	"dark_gray":    "#303030",
	"blue":         "#B2CCD6",
	"green":        "#353535",
	"cyan":         "#EEFFFF",
	"red":          "#F78C6C",
	"magenta":      "#FF5370",
	"yellow":       "#4A4A4A",
	"white":        "#EEFFFF",
	"screen_colors": "white,black",
	"popup_colors":  "dark_magenta,gray"
}
